{
	"backtraceGraph" : 
	{
		"commands" : 
		[
			"install"
		],
		"files" : 
		[
			"client/cpr/cpr/CMakeLists.txt"
		],
		"nodes" : 
		[
			{
				"file" : 0
			},
			{
				"command" : 0,
				"file" : 0,
				"line" : 80,
				"parent" : 0
			}
		]
	},
	"installers" : 
	[
		{
			"backtrace" : 1,
			"component" : "Unspecified",
			"destination" : "lib",
			"paths" : 
			[
				"client/cpr/cpr/libcpr.so.1.9.0",
				"client/cpr/cpr/libcpr.so.1"
			],
			"targetId" : "cpr::@d0d141491d64b303c231",
			"targetIndex" : 0,
			"targetInstallNamelink" : "skip",
			"type" : "target"
		},
		{
			"backtrace" : 1,
			"component" : "Unspecified",
			"destination" : "lib",
			"paths" : 
			[
				"client/cpr/cpr/libcpr.so"
			],
			"targetId" : "cpr::@d0d141491d64b303c231",
			"targetIndex" : 0,
			"targetInstallNamelink" : "only",
			"type" : "target"
		}
	],
	"paths" : 
	{
		"build" : "client/cpr/cpr",
		"source" : "client/cpr/cpr"
	}
}
